lsst/__init__.py
lsst/rucio/__init__.py
lsst/rucio/register/__init__.py
lsst/rucio/register/app_parser.py
lsst/rucio/register/data_type.py
lsst/rucio/register/dataset_map.py
lsst/rucio/register/export.py
lsst/rucio/register/resource_bundle.py
lsst/rucio/register/rubin_meta.py
lsst/rucio/register/rucio_did.py
lsst/rucio/register/rucio_interface.py
lsst/rucio/register/rucio_register_config.py
lsst/rucio/register/script.py
lsst/rucio/register/version.py
lsst_rucio_register-30.0.0.dist-info/licenses/LICENSE
lsst_rucio_register-30.0.0.dist-info/METADATA
lsst_rucio_register-30.0.0.dist-info/WHEEL
lsst_rucio_register-30.0.0.dist-info/entry_points.txt
lsst_rucio_register-30.0.0.dist-info/top_level.txt
lsst_rucio_register-30.0.0.dist-info/zip-safe
lsst_rucio_register-30.0.0.dist-info/RECORD
