Metadata-Version: 2.4
Name: lsst-rucio-register
Version: 30.0.0
Summary: Tools for registering LSST metadata information into Rucio
Author-email: Rubin Observatory Data Management <dm-admin@lists.lsst.org>
License-Expression: GPL-3.0-or-later
Project-URL: Homepage, https://github.com/lsst/rucio_register
Keywords: lsst
Classifier: Intended Audience :: Science/Research
Classifier: Operating System :: OS Independent
Classifier: Programming Language :: Python :: 3
Classifier: Programming Language :: Python :: 3.14
Classifier: Programming Language :: Python :: 3.13
Classifier: Programming Language :: Python :: 3.12
Classifier: Programming Language :: Python :: 3.11
Classifier: Topic :: Scientific/Engineering :: Astronomy
Requires-Python: >=3.11.0
License-File: LICENSE
Requires-Dist: pyyaml>=5.1
Requires-Dist: lsst-utils
Requires-Dist: lsst-daf-butler
Requires-Dist: pydantic<3.0,>=2
Requires-Dist: rucio-clients
Dynamic: license-file
